odoo10_addon_partner_phonecall_schedule-10.0.1.0.0-py2.7-nspkg.pth
odoo/addons/partner_phonecall_schedule/README.rst
odoo/addons/partner_phonecall_schedule/__init__.py
odoo/addons/partner_phonecall_schedule/__openerp__.py
odoo/addons/partner_phonecall_schedule/i18n/es.po
odoo/addons/partner_phonecall_schedule/models/__init__.py
odoo/addons/partner_phonecall_schedule/models/res_partner.py
odoo/addons/partner_phonecall_schedule/security/ir.model.access.csv
odoo/addons/partner_phonecall_schedule/static/description/icon.png
odoo/addons/partner_phonecall_schedule/tests/__init__.py
odoo/addons/partner_phonecall_schedule/tests/test_schedule.py
odoo/addons/partner_phonecall_schedule/views/res_partner_view.xml
odoo10_addon_partner_phonecall_schedule-10.0.1.0.0.dist-info/DESCRIPTION.rst
odoo10_addon_partner_phonecall_schedule-10.0.1.0.0.dist-info/METADATA
odoo10_addon_partner_phonecall_schedule-10.0.1.0.0.dist-info/RECORD
odoo10_addon_partner_phonecall_schedule-10.0.1.0.0.dist-info/WHEEL
odoo10_addon_partner_phonecall_schedule-10.0.1.0.0.dist-info/metadata.json
odoo10_addon_partner_phonecall_schedule-10.0.1.0.0.dist-info/namespace_packages.txt
odoo10_addon_partner_phonecall_schedule-10.0.1.0.0.dist-info/top_level.txt
